board/__init__.py
board/board.py
board/vector.py
oboard-0.4.0.dist-info/LICENSE
oboard-0.4.0.dist-info/METADATA
oboard-0.4.0.dist-info/WHEEL
oboard-0.4.0.dist-info/top_level.txt
oboard-0.4.0.dist-info/RECORD
