Metadata-Version: 2.1
Name: oboard
Version: 0.4.0
Summary: Module for dynamic object-based two-dimensional board functionality
Home-page: https://github.com/jennissenevan/oboard
Author: Evan Jennissen
Author-email: jennissenevan@gmail.com
Classifier: Programming Language :: Python :: 3
Classifier: License :: OSI Approved :: MIT License
Classifier: Operating System :: OS Independent
Requires-Python: >=3.9
License-File: LICENSE
Requires-Dist: bidict
